watermarker/__init__.py
watermarker/admin.py
watermarker/conf.py
watermarker/models.py
watermarker/utils.py
watermarker/locale/ru/LC_MESSAGES/django.mo
watermarker/locale/ru/LC_MESSAGES/django.po
watermarker/migrations/0001_initial.py
watermarker/migrations/0002_auto_20210320_2145.py
watermarker/migrations/__init__.py
watermarker/templatetags/__init__.py
watermarker/templatetags/watermark.py
watermarker/tests/__init__.py
watermarker/tests/conftest.py
watermarker/tests/models.py
watermarker/tests/settings.py
watermarker/tests/test_utils.py
django_watermark-0.2.0.dist-info/LICENSE
django_watermark-0.2.0.dist-info/METADATA
django_watermark-0.2.0.dist-info/WHEEL
django_watermark-0.2.0.dist-info/top_level.txt
django_watermark-0.2.0.dist-info/RECORD
